


> Written with [StackEdit](https://stackedit.io/).


## Final 类型的常量

```java
package com.lsl.day12;  
  
public class Demo1 {  
    public static void main(String[] args) {  
        System.out.println(FinalTest.x);  
  }  
}  
  
class FinalTest {  
    public static final int x = 3;  
  
 static {  
        System.out.println("FinalTest static block");  
  }  
}
```

输出：

```java
3
```

上述的程序只输出了一个 3，而没有执行静态代码块中的内容，也就意味着 FinalTest 这个类没有被初始化。为什么呢？我们把 Demo1.class 使用如下命令反编译看看

```java
javap -c Demo1
```

如下

```java
Compiled from "Demo1.java"
public class com.lsl.day12.Demo1 {
  public com.lsl.day12.Demo1();
    Code:
       0: aload_0
       1: invokespecial #1                  // Method java/lang/Object."<init>":()V
       4: return

  public static void main(java.lang.String[]);
    Code:
       0: getstatic     #2                  // Field java/lang/System.out:Ljava/io/PrintStream;
       3: iconst_3
       4: invokevirtual #4                  // Method java/io/PrintStream.println:(I)V
       7: return
}

```

从反编译出来的内容我们可以看到，在 main 方法中，有一个 iconst_3 , 也就是说，**当上述程序编译好之后，final 类型的编译期常量 x 就会被保存到调用它的方法所属的类的常量池中**，可以认为，上述程序编译好之后，就和 FinalTest 类没有任何关系了。

如果我们将 FinalTest 类中的常量换成静态变量，也就是把 final 去掉：

```java
public static int x = 3;
```

这个时候的运行结果如下：

```java
FinalTest static block
3
```

从输出结果可以看出，这个时候，FinalTest 类被初始化了，因为静态代码块中的内容执行了。

那么，我们再将 Demo1.class 反编译出来看看：

```java
       1: invokespecial #1                  // Method java/lang/Object."<init>":()V
       4: return

  public static void main(java.lang.String[]);
    Code:
       0: getstatic     #2                  // Field java/lang/System.out:Ljava/io/PrintStream;
       3: getstatic     #3                  // Field com/lsl/day12/FinalTest.x:I
       6: invokevirtual #4                  // Method java/io/PrintStream.println:(I)V
       9: return
}
```

从 main 方法中可以看出，调用了 FinalTest.x ，也就是调用了 FinalTest 类中的静态变量：

```java
3: getstatic     #3                  // Field com/lsl/day12/FinalTest.x:I
```

而之前我们说过，调用一个类的静态变量或者静态方法会对这个类主动使用，也就是这个类会被初始化。所以上述的 FinalTest 中的静态代码块会被执行。

接着我们将 FinalTest 类中的 x 做如下改变：

```java
public static final int x = new Random().nextInt(10);
```

其他的都不变，这个时候输出如下：

```java
FinalTest static block
9
```

可以看出，FinalTest 类中的 静态代码块 也被执行了。

原因是 `new Random().nextInt(10)` 在编译期不能被确认的。也就是说此时的 x 是一个运行期常量，而不是编译期常量。



## 子类和父类

直接看程序：

```java
package com.lsl.day12;  
  
public class Demo2 {  
  
    static {  
        System.out.println("Demo2 static block");  
  }  
  
    public static void main(String[] args) {  
        System.out.println(Child.b);  
  }  
}  
  
class Parent {  
    static int a = 3;  
  
 static {  
        System.out.println("Parent static block");  
  }  
}  
  
class Child extends Parent {  
    static int b = 4;  
  
 static {  
        System.out.println("Child static block");  
  }  
}
```

上述程序中，我们定义了 3 个类，分别是 Demo2，Parent，Child；他们三个类中都有一个静态变量和一个静态代码块。并且 Child 继承自 Parent，然后我们在启动类 Demo2 中输出了 `Child.b` 。

输出结果如下：

```java
Demo2 static block
Parent static block
Child static block
4
```
也就是说当一个子类被初始化的时候，其父类会先被初始化，直到父类初始化完毕，子类才初始化。我们可以把上面 3 个类的加载顺序打印出来看看。

将 VM options 的参数设置为 `-XX:+TraceClassLoading`  然后再次运行，部分输出如下：

```shell
[Loaded day12.Demo2 from file:/...
...
[Loaded day12.Parent from file:/...
[Loaded day12.Child from file:/...
...
```

可以看出，加载顺序也是先加载启动类 Demo2，接着是 Parent ，最后才是 Child。

## Demo2

```java
public class Demo2 {
    static {
        System.out.println("Demo2 static block");
    }

    public static void main(String[] args) {
        Parent2 parent2;

        System.out.println("---------");

        parent2 = new Parent2();

        System.out.println("---------");

        System.out.println(parent2.a);

        System.out.println("---------");

        System.out.println(Child2.b);
    }
}

class Parent2 {
    static int a = 3;

    static {
        System.out.println("Parent static block");
    }
}

class Child2 extends Parent2 {
    static int b = 4;

    static {
        System.out.println("Child static block");
    }
}
```
输出：

```shell
Demo2 static block
---------
Parent static block
---------
3
---------
Child static block
4
```

以上例子说明一个类只会被初始化一次。如上面你的 Parent2 类

## Demo3

```java
public class Demo3 {
    public static void main(String[] args) {
        System.out.println(Child3.a);
        System.out.println("------");
        Child3.doSomething();
    }
}

class Parent3 {
    static int a = 3;

    static {
        System.out.println("Parent3 static block");
    }

    static void doSomething() {
        System.out.println("do something");
    }
}

class Child3 extends Parent3 {
    static {
        System.out.println("Child3 static block");
    }
}
```
输出：

```shell
Parent3 static block
3
------
do something
```
说明：如果我们使用子类去调用父类的静态变量或者方法，表示的是对父类的主动使用（会导致父类初始化），子类不会被初始化；也就是说静态变量或方法被定义在哪个类，哪个类机会被主动使用，而不看调用者是谁。

## Demo4

```java
public class Demo4 {
    public static void main(String[] args) throws ClassNotFoundException {
        // 获取系统类加载器
        ClassLoader loader = ClassLoader.getSystemClassLoader();
        Class<?> clazz = loader.loadClass("day12.CL");
        System.out.println(clazz);
        System.out.println("---------");
        clazz = Class.forName("day12.CL");
        System.out.println(clazz);
    }
}

class CL {
    static {
        System.out.println("Class CL");
    }
}
```

输出：

```shell
class day12.CL
---------
Class CL
class day12.CL
```


结论：
	调动 ClassLoader 类的 loadClass 方法加载一个类，并不是对类的主动使用，不会导致类的初始化。
	而 `Class.forName(...)`  的方式来获取类的 class 对象，使用的是反射的方式，而反射会导致当前类被主动使用，也就是当前类会被初始化。
<!--stackedit_data:
eyJoaXN0b3J5IjpbMTkzNzA4NzUwXX0=
-->